jvalue.py
jvalue-0.1.0.dist-info/LICENSE
jvalue-0.1.0.dist-info/WHEEL
jvalue-0.1.0.dist-info/METADATA
jvalue-0.1.0.dist-info/RECORD
