Metadata-Version: 2.3
Name: jvalue
Version: 0.1.0
Summary: Extract value from json via simple json path.
Requires-Python: >=3.8
Classifier: License :: OSI Approved :: MIT License
